cypresstestapi/__init__.py
cypresstestapi/api_helper.py
cypresstestapi/configuration.py
cypresstestapi/cypresstestapi_client.py
cypresstestapi/controllers/__init__.py
cypresstestapi/controllers/api_controller.py
cypresstestapi/controllers/base_controller.py
cypresstestapi/exceptions/__init__.py
cypresstestapi/exceptions/api_exception.py
cypresstestapi/http/__init__.py
cypresstestapi/http/http_call_back.py
cypresstestapi/http/http_method_enum.py
cypresstestapi/http/http_request.py
cypresstestapi/http/http_response.py
cypresstestapi/models/__init__.py
cypresstestapi/models/custom_enum.py
cypresstestapi/models/deer.py
cypresstestapi/models/item.py
cypresstestapi/models/item_response.py
cypresstestapi/models/lion.py
cypresstestapi/models/message.py
cypresstestapi/models/message_2.py
cypresstestapi/models/multiple_arrays_request.py
cypresstestapi/models/nac_tag.py
cypresstestapi/models/o_auth_scope_o_auth_acg_enum.py
cypresstestapi/models/response_http_400.py
cypresstestapi/models/response_http_404.py
cypresstestapi/models/status_11_enum.py
cypresstestapi/models/status_1_enum.py
cypresstestapi/models/status_enum.py
cypresstestapi/models/tokens_request.py
cypresstestapi/utilities/__init__.py
cypresstestapi/utilities/file_wrapper.py
uta_cotton_sdk-6.6.8.dist-info/licenses/LICENSE
uta_cotton_sdk-6.6.8.dist-info/METADATA
uta_cotton_sdk-6.6.8.dist-info/WHEEL
uta_cotton_sdk-6.6.8.dist-info/top_level.txt
uta_cotton_sdk-6.6.8.dist-info/RECORD
